proton_api/__init__.py
proton_api/api_client.py
proton_api/auth_api.py
proton_api/configuration.py
proton_api/environment.py
proton_api/rest.py
proton_api/api/__init__.py
proton_api/api/annuities_api.py
proton_api/api/business_financial_management_api.py
proton_api/api/cards_api.py
proton_api/api/financial_health_api.py
proton_api/api/financial_planning_api.py
proton_api/api/goals_api.py
proton_api/api/life_insurance_api.py
proton_api/api/personal_financial_management_api.py
proton_api/api/portfolio_construction_api.py
proton_api/api/portfolio_management_api.py
proton_api/api/risk_scoring_api.py
proton_api/api/simulations_api.py
proton_api/api/util_api.py
proton_api/models/__init__.py
proton_api/models/accumulation_goal_deposit_config.py
proton_api/models/annuity_calculator_accumulation_horizon_request.py
proton_api/models/annuity_calculator_annuity_amount_request.py
proton_api/models/annuity_calculator_decumulation_horizon_request.py
proton_api/models/annuity_calculator_deposit_amount_request.py
proton_api/models/annuity_calculator_initial_balance_request.py
proton_api/models/annuity_deposit_schedule.py
proton_api/models/answer.py
proton_api/models/backtest_request.py
proton_api/models/beneficiary_bequest_config.py
proton_api/models/budget_aggregation_account.py
proton_api/models/budget_calculator_request.py
proton_api/models/budget_component.py
proton_api/models/budget_details.py
proton_api/models/business_financial_health_check_request.py
proton_api/models/business_invoice_analysis_request.py
proton_api/models/calculator_deposit_schedule.py
proton_api/models/calculator_deposit_schedule1.py
proton_api/models/card_analysis_request.py
proton_api/models/card_limit_check_request.py
proton_api/models/card_transaction_authorization_request.py
proton_api/models/cash_analysis_request.py
proton_api/models/cash_flow_analysis_request.py
proton_api/models/children_education_config.py
proton_api/models/customer_analysis_request.py
hydrogen_proton_api-1.9.2.dist-info/METADATA
hydrogen_proton_api-1.9.2.dist-info/WHEEL
hydrogen_proton_api-1.9.2.dist-info/top_level.txt
hydrogen_proton_api-1.9.2.dist-info/RECORD
